README.md
setup.cfg
setup.py
slyce/__init__.py
slyce/credentials.py
slyce/exception.py
slyce.egg-info/PKG-INFO
slyce.egg-info/SOURCES.txt
slyce.egg-info/dependency_links.txt
slyce.egg-info/requires.txt
slyce.egg-info/top_level.txt
slyce/client/__init__.py
slyce/client/abstract.py
slyce/client/account.py
slyce/client/admin.py
slyce/protobufgen/__init__.py
slyce/protobufgen/auth_grpc.py
slyce/protobufgen/auth_pb2.py
slyce/protobufgen/classifier_grpc.py
slyce/protobufgen/classifier_pb2.py
slyce/protobufgen/common_grpc.py
slyce/protobufgen/common_pb2.py
slyce/protobufgen/image_grpc.py
slyce/protobufgen/image_pb2.py
slyce/protobufgen/search_grpc.py
slyce/protobufgen/search_pb2.py
slyce/protobufgen/workflow_grpc.py
slyce/protobufgen/workflow_pb2.py