Metadata-Version: 2.1
Name: slyce
Version: 0.2.0
Summary: Python library for calling Slyce API.
Home-page: https://slyce-inc.github.io/forgex.lib.slycepy/_build/html/index.html
Author: Slyce Dev
Author-email: dev@slyce.it
License: MIT
Platform: any
Requires-Python: >=3.7
